package/__init__.py
package/modul1.py
package/modul2.py
projekt_bla_stefan-1.0.0.dist-info/METADATA
projekt_bla_stefan-1.0.0.dist-info/WHEEL
projekt_bla_stefan-1.0.0.dist-info/top_level.txt
projekt_bla_stefan-1.0.0.dist-info/RECORD
